LICENSE
MANIFEST.in
README.rst
setup.py
kotocore/__init__.py
kotocore/cache.py
kotocore/collections.py
kotocore/connection.py
kotocore/exceptions.py
kotocore/introspection.py
kotocore/loader.py
kotocore/resources.py
kotocore/session.py
kotocore.egg-info/PKG-INFO
kotocore.egg-info/SOURCES.txt
kotocore.egg-info/dependency_links.txt
kotocore.egg-info/requires.txt
kotocore.egg-info/top_level.txt
kotocore/data/aws/resources/cloudsearch-2011-02-01.json
kotocore/data/aws/resources/dynamodb-2012-08-10.json
kotocore/data/aws/resources/elasticache-2013-06-15.json
kotocore/data/aws/resources/elastictranscoder-2012-09-25.json
kotocore/data/aws/resources/glacier-2012-06-01.json
kotocore/data/aws/resources/iam-2010-05-08.json
kotocore/data/aws/resources/s3-2006-03-01.json
kotocore/data/aws/resources/ses-2010-12-01.json
kotocore/data/aws/resources/sns-2010-03-31.json
kotocore/data/aws/resources/sqs-2012-11-05.json
kotocore/data/aws/resources/support-2013-04-15.json
kotocore/utils/__init__.py
kotocore/utils/constants.py
kotocore/utils/import_utils.py
kotocore/utils/mangle.py