Metadata-Version: 1.0
Name: kotocore
Version: 0.1.2
Summary: Utility for botocore.
Home-page: https://github.com/henrysher/kotocore
Author: Henry Huang
Author-email: henry.s.huang@gmail.com
License: Apache License
